MongodbRumenZhinan/README.md
MongodbRumenZhinan/__init__.py
MongodbRumenZhinan/__main__.py
MongodbRumenZhinan/file.epub
MongodbRumenZhinan/index.html
MongodbRumenZhinan/css/__init__.py
MongodbRumenZhinan/css/annotations.css
MongodbRumenZhinan/css/main.css
MongodbRumenZhinan/css/normalize.css
MongodbRumenZhinan/css/popup.css
MongodbRumenZhinan/font/__init__.py
MongodbRumenZhinan/font/fontello.eot
MongodbRumenZhinan/font/fontello.svg
MongodbRumenZhinan/font/fontello.ttf
MongodbRumenZhinan/font/fontello.woff
MongodbRumenZhinan/img/__init__.py
MongodbRumenZhinan/img/annotator-glyph-sprite.png
MongodbRumenZhinan/img/annotator-icon-sprite.png
MongodbRumenZhinan/img/apple-touch-icon.png
MongodbRumenZhinan/img/cancelfullscreen.png
MongodbRumenZhinan/img/close.png
MongodbRumenZhinan/img/fullscreen.png
MongodbRumenZhinan/img/loader.gif
MongodbRumenZhinan/img/menu-icon.png
MongodbRumenZhinan/img/save.png
MongodbRumenZhinan/img/saved.png
MongodbRumenZhinan/img/settings-s.png
MongodbRumenZhinan/img/settings.png
MongodbRumenZhinan/img/star.png
MongodbRumenZhinan/js/__init__.py
MongodbRumenZhinan/js/epub.js
MongodbRumenZhinan/js/epub.min.js
MongodbRumenZhinan/js/epub.min.map
MongodbRumenZhinan/js/hooks.min.js
MongodbRumenZhinan/js/hooks.min.map
MongodbRumenZhinan/js/reader.js
MongodbRumenZhinan/js/reader.js.map
MongodbRumenZhinan/js/reader.min.js
MongodbRumenZhinan/js/reader.min.map
MongodbRumenZhinan/js/hooks/__init__.py
MongodbRumenZhinan/js/hooks/extensions/__init__.py
MongodbRumenZhinan/js/hooks/extensions/highlight.js
MongodbRumenZhinan/js/libs/__init__.py
MongodbRumenZhinan/js/libs/jquery.min.js
MongodbRumenZhinan/js/libs/localforage.min.js
MongodbRumenZhinan/js/libs/screenfull.js
MongodbRumenZhinan/js/libs/screenfull.min.js
MongodbRumenZhinan/js/libs/zip.min.js
MongodbRumenZhinan/js/plugins/__init__.py
MongodbRumenZhinan/js/plugins/hypothesis.js
MongodbRumenZhinan/js/plugins/search.js
mongodb_rumen_zhinan-2024.3.3.0.dist-info/METADATA
mongodb_rumen_zhinan-2024.3.3.0.dist-info/WHEEL
mongodb_rumen_zhinan-2024.3.3.0.dist-info/entry_points.txt
mongodb_rumen_zhinan-2024.3.3.0.dist-info/top_level.txt
mongodb_rumen_zhinan-2024.3.3.0.dist-info/RECORD
